{
  "posts": [
    {
      "id": 4,
      "title": "제목 예시 4",
      "contents": "4444444444",
      "createdAt": "2020-01-04"
    },
    {
      "id": 7,
      "title": "제목 예시 7",
      "contents": "7777777777",
      "createdAt": "2020-01-07"
    },
    {
      "id": 11,
      "title": "제목 예시 11",
      "contents": "11111111111123123111",
      "createdAt": "2020-01-11"
    },
    {
      "id": 12,
      "title": "제목 예시 12",
      "contents": "12121212121212",
      "createdAt": "2020-01-12"
    },
    {
      "title": "asdfa",
      "contents": "sdfasdf",
      "createdAt": 1658320752316,
      "id": 13
    },
    {
      "title": "asdfasd",
      "contents": "fasdfadsfad",
      "createdAt": 1658320755281,
      "id": 14
    },
    {
      "title": "asdfasdfa",
      "contents": "sdfasdfadsf",
      "createdAt": 1658320758322,
      "id": 15
    }
  ]
}